wesnothanalytics/__init__.py
wesnothanalytics/classes.py
wesnothanalytics/main.py
wesnothanalytics/util.py
wesnothanalytics/configs/flags.json
wesnothanalytics/configs/unit_db.json
wesnothanalytics-0.1.7.dist-info/METADATA
wesnothanalytics-0.1.7.dist-info/WHEEL
wesnothanalytics-0.1.7.dist-info/top_level.txt
wesnothanalytics-0.1.7.dist-info/RECORD
