Metadata-Version: 2.4
Name: wesnothanalytics
Version: 0.1.7
Summary: A simple replay file parser for the game 'Battle for Wesnoth'
Author-email: Dark Adept <wesnothanalytics@gmail.com>
Project-URL: Homepage, https://github.com/dark-adept/wesnothanalytics
Classifier: Programming Language :: Python :: 3
Classifier: License :: OSI Approved :: MIT License
Classifier: Operating System :: OS Independent
Requires-Python: >=3.8
